apexsearch/__init__.py
apexsearch/search.py
apex_search-0.0.1.dist-info/LICENSE
apex_search-0.0.1.dist-info/METADATA
apex_search-0.0.1.dist-info/WHEEL
apex_search-0.0.1.dist-info/top_level.txt
apex_search-0.0.1.dist-info/RECORD
